MANIFEST.in
README
setup.cfg
setup.py
cormoran/__init__.py
cormoran/fields.py
cormoran/persistence.py
cormoran/persistent.py
cormoran/resultset.py
cormoran/store.py
cormoran.egg-info/PKG-INFO
cormoran.egg-info/SOURCES.txt
cormoran.egg-info/dependency_links.txt
cormoran.egg-info/top_level.txt
cormoran/backends/__init__.py
cormoran/backends/sqlite.py
cormoran/sql/__init__.py
cormoran/sql/statements.py
docs/Makefile
docs/make.bat
docs/source/conf.py
docs/source/index.rst
docs/source/tutorial.rst
docs/source/library/index.rst
docs/source/library/persistent.rst
docs/source/library/store.rst
docs/source/releases/index.rst
docs/source/releases/v0.1.rst
tests/__init__.py
tests/unit/__init__.py
tests/unit/test_fields.py
tests/unit/test_persistence.py
tests/unit/test_persistent.py
tests/unit/test_resultset.py
tests/unit/test_store.py
tests/unit/sql/__init__.py
tests/unit/sql/test_statements.py