Metadata-Version: 1.0
Name: cormoran
Version: 0.1
Summary: Cormoran is a fast and lightweight persistence framework
Home-page: https://github.com/jaimegildesagredo/cormoran
Author: Jaime Gil de Sagredo Luna
Author-email: jaimegildesagredo@gmail.com
License: GPLv3
Download-URL: https://github.com/jaimegildesagredo/cormoran/downloads
Platform: UNKNOWN
Classifier: Development Status :: 3 - Alpha
Classifier: Intended Audience :: Developers
Classifier: License :: OSI Approved :: GNU General Public License (GPL)
Classifier: Natural Language :: English
Classifier: Operating System :: OS Independent
Classifier: Programming Language :: Python
Classifier: Topic :: Database :: Front-Ends
Classifier: Topic :: Software Development :: Libraries :: Python Modules
